arrow_json-0.9.0.dist-info/METADATA
arrow_json-0.9.0.dist-info/WHEEL
arrow_json/py.typed
arrow_json/_arrow_json.pyi
arrow_json/__init__.py
arrow_json/_arrow_json.pypy38-pp73-aarch64-linux-gnu.so
arrow_json-0.9.0.dist-info/RECORD
