Metadata-Version: 2.1
Name: arrow-json
Version: 0.9.0
Classifier: Development Status :: 3 - Alpha
Classifier: Intended Audience :: Developers
Classifier: License :: OSI Approved :: MIT License
Classifier: Topic :: Software Development
Classifier: Topic :: Software Development :: Libraries
Classifier: Topic :: Software Development :: Libraries :: Python Modules
Requires-Dist: pyarrow>=11
Requires-Dist: typing-extensions>=3; python_version < '3.8'
Requires-Dist: pytest>=7.0.0; extra == 'test'
Requires-Dist: maturin>= 1.0.0; extra == 'test'
Requires-Dist: pre-commit>= 2.16.0; extra == 'test'
Requires-Dist: pyarrow>= 11.0.0; extra == 'test'
Requires-Dist: polars>= 0.16.1; extra == 'test'
Provides-Extra: test
Provides-Extra: bench
Summary: Arrow -> JSON encoder
Author: Adrian Garcia Badaracco
License: MIT
Requires-Python: >=3.7
Project-URL: repository, https://github.com/adriangb/pgpq
Project-URL: documentation, https://github.com/adriangb/pgpq/README.md
Project-URL: homepage, https://github.com/adriangb/pgpq
